pyquery/__init__.py
pyquery/cssselectpatch.py
pyquery/openers.py
pyquery/pyquery.py
pyquery/text.py
pyquery-1.4.2.dist-info/LICENSE.txt
pyquery-1.4.2.dist-info/METADATA
pyquery-1.4.2.dist-info/WHEEL
pyquery-1.4.2.dist-info/entry_points.txt
pyquery-1.4.2.dist-info/top_level.txt
pyquery-1.4.2.dist-info/RECORD
