Metadata-Version: 2.1
Name: pyquery
Version: 1.4.2
Summary: A jquery-like library for python
Home-page: https://github.com/gawel/pyquery
Author: Olivier Lauzanne
Author-email: olauzanne@gmail.com
Maintainer: Gael Pasgrimaud
Maintainer-email: gael@gawel.org
License: BSD
Keywords: jquery html xml scraping
Platform: UNKNOWN
Classifier: Intended Audience :: Developers
Classifier: Development Status :: 5 - Production/Stable
Classifier: Programming Language :: Python :: 3
Classifier: Programming Language :: Python :: 3.5
Classifier: Programming Language :: Python :: 3.6
Classifier: Programming Language :: Python :: 3.7
Requires-Dist: lxml (>=2.1)
Requires-Dist: cssselect (>0.7.9)
